CHANGELOG
LICENSE
MANIFEST.in
README
setup.cfg
setup.py
scatterbytes/__init__.py
scatterbytes/chunk.py
scatterbytes/config.py
scatterbytes/crypt.py
scatterbytes/errors.py
scatterbytes/https.py
scatterbytes/node.py
scatterbytes/util.py
scatterbytes/xmlrpc.py
scatterbytes.egg-info/PKG-INFO
scatterbytes.egg-info/SOURCES.txt
scatterbytes.egg-info/dependency_links.txt
scatterbytes.egg-info/top_level.txt
scatterbytes/client/__init__.py
scatterbytes/client/chunk.py
scatterbytes/client/downloader.py
scatterbytes/client/node.py
scatterbytes/client/util.py
scatterbytes/client/xmlrpc.py
scatterbytes/compat/__init__.py
scatterbytes/compat/ordereddict.py
scatterbytes/storage/__init__.py
scatterbytes/storage/node.py
scatterbytes/storage/xmlrpc.py
scatterbytes/testing/__init__.py
scatterbytes/testing/node.py
scatterbytes/testing/test_client.py
scatterbytes/testing/test_client_chunk.py
scatterbytes/testing/test_config.py
scatterbytes/testing/test_crypt.py
scatterbytes/testing/test_downloader.py
scatterbytes/testing/test_https_common.py
scatterbytes/testing/test_m2_http.py
scatterbytes/testing/test_node_common.py
scatterbytes/testing/test_storagenode.py
scatterbytes/testing/test_storagenodeserver.py
scatterbytes/testing/test_xmlrpc.py
scatterbytes/testing/tls.py
scatterbytes/testing/util.py
scripts/sbnet