Metadata-Version: 1.0
Name: scatterbytes
Version: 0.8.8
Summary: Library and CLI for accessing the ScatterBytes Network
Home-page: https://www.scatterbytes.net
Author: Randall Smith
Author-email: randall@scatterbytes.net
License: BSD License
Platform: UNKNOWN
Classifier: Development Status :: 4 - Beta
Classifier: Environment :: Console
Classifier: Intended Audience :: Information Technology
Classifier: Intended Audience :: System Administrators
Classifier: Intended Audience :: Developers
Classifier: License :: OSI Approved :: BSD License
Classifier: Programming Language :: Python
Classifier: Operating System :: OS Independent
Classifier: Topic :: Internet
Classifier: Topic :: System :: Archiving :: Backup
Classifier: Topic :: System :: Distributed Computing
